netsky/__init__.py
netsky/__main__.py
netsky/ai.py
netsky/app.py
netsky/classifiers.py
netsky/functions.py
netsky/models.py
netsky/states.py
netsky/systems.py
netsky/commands/__init__.py
netsky/commands/ai.py
netsky/commands/testing.py
netsky/tools/__init__.py
netsky/tools/birdbrain.py
netsky/tools/code.py
netsky/tools/filesystem.py
netsky/tools/internet.py
netsky/tools/text.py
netsky-0.0.11.dist-info/METADATA
netsky-0.0.11.dist-info/WHEEL
netsky-0.0.11.dist-info/entry_points.txt
netsky-0.0.11.dist-info/licenses/LICENSE
netsky-0.0.11.dist-info/RECORD
