Metadata-Version: 2.1
Name: netsky
Version: 0.0.11
Summary: not skynet, obviously
Project-URL: Homepage, https://github.com/lostmygithubaccount/netsky
Project-URL: Bug Tracker, https://github.com/lostmygithubaccount/netsky/issues
Author-email: Cody <cody@dkdc.dev>
License-File: LICENSE
Classifier: License :: OSI Approved :: MIT License
Classifier: Operating System :: OS Independent
Classifier: Programming Language :: Python :: 3
Requires-Python: >=3.11
Requires-Dist: html2text
Requires-Dist: ibis-framework[deltalake,duckdb,polars]
Requires-Dist: ipython
Requires-Dist: marvin[ddg]~=1.3.0
Requires-Dist: openai
Requires-Dist: pillow
Requires-Dist: plotly
Requires-Dist: python-dotenv
Requires-Dist: requests
Requires-Dist: streamlit
Requires-Dist: toml
Requires-Dist: typer[all]
